cocotbext/spi/__init__.py
cocotbext/spi/_version.py
cocotbext/spi/about.py
cocotbext/spi/exceptions.py
cocotbext/spi/spi.py
cocotbext/spi/devices/generic.py
cocotbext/spi/devices/ADI/ADXL345.py
cocotbext/spi/devices/ADI/__init__.py
cocotbext/spi/devices/TI/ADS8028.py
cocotbext/spi/devices/TI/DRV8304.py
cocotbext/spi/devices/TI/__init__.py
cocotbext/spi/devices/Trinamic/TMC4671.py
cocotbext/spi/devices/Trinamic/__init__.py
cocotbext_spi-0.4.0.dist-info/COPYING
cocotbext_spi-0.4.0.dist-info/METADATA
cocotbext_spi-0.4.0.dist-info/WHEEL
cocotbext_spi-0.4.0.dist-info/top_level.txt
cocotbext_spi-0.4.0.dist-info/RECORD
