Metadata-Version: 2.1
Name: cocotbext-spi
Version: 0.4.0
Summary: SPI modules for cocotb
Author-email: Spencer Chang <spencer@sycee.xyz>
License: MIT
Project-URL: repository, https://github.com/schang412/cocotbext-spi
Classifier: Development Status :: 3 - Alpha
Classifier: Programming Language :: Python :: 3
Classifier: License :: OSI Approved :: MIT License
Classifier: Operating System :: OS Independent
Classifier: Topic :: Scientific/Engineering :: Electronic Design Automation (EDA)
Requires-Python: >=3.7
License-File: COPYING
Requires-Dist: cocotb >=1.6
Requires-Dist: cocotb-bus >=0.2.1
